GA/GA.py
GA/__init__.py
GA_fiachia-2.0.5.dist-info/METADATA
GA_fiachia-2.0.5.dist-info/WHEEL
GA_fiachia-2.0.5.dist-info/licence.txt
GA_fiachia-2.0.5.dist-info/top_level.txt
GA_fiachia-2.0.5.dist-info/RECORD
